eztool/__init__.py
eztool/json_worker.py
eztool/og.py
eztool/pyxl_handler.py
eztool/timer.py
eztool/xw_handler.py
eztool-0.0.4.dist-info/LICENSE
eztool-0.0.4.dist-info/METADATA
eztool-0.0.4.dist-info/WHEEL
eztool-0.0.4.dist-info/top_level.txt
eztool-0.0.4.dist-info/RECORD
